hakoniwa/__init__.py
hakoniwa/cli.py
hakoniwa/context.py
hakoniwa/entity/__init__.py
hakoniwa/entity/dynamic_entity.py
hakoniwa/entity/entity.py
hakoniwa/entity/hello_entity.py
hakoniwa/entity/openai_entity.py
hakoniwa/environment.py
hakoniwa/state.py
hakoniwa-0.1.2.dist-info/LICENSE
hakoniwa-0.1.2.dist-info/WHEEL
hakoniwa-0.1.2.dist-info/entry_points.txt
hakoniwa-0.1.2.dist-info/METADATA
hakoniwa-0.1.2.dist-info/RECORD
