Metadata-Version: 2.1
Name: hakoniwa
Version: 0.1.2
Summary: 
Author: Kai Sasaki
Author-email: lewuathe@gmail.com
Requires-Python: >=3.10,<4.0
Classifier: Programming Language :: Python :: 3
Classifier: Programming Language :: Python :: 3.10
Classifier: Programming Language :: Python :: 3.11
Requires-Dist: openai (>=0.27.8,<0.28.0)
Requires-Dist: torch (>=2.0.1,<3.0.0)
Requires-Dist: transformers (>=4.31.0,<5.0.0)
